{"subjects": ["gn:promo:LIVE:041"],
"meta": "NULL",
"name": "pn:promo:LIVE:041",
"actions": ["an:promo:LIVE:dummy:state:0:all:NA"],
"conditions": {},
"effect": "allow",
"resources": ["rn:promo:LIVE:subcategory:041-071-071:*",
"rn:promo:LIVE:subcategory:041-016-016:*",
"rn:promo:LIVE:subcategory:041-030-039:*",
"rn:promo:LIVE:subcategory:041-001-001:*",
"rn:promo:LIVE:subcategory:041-010-010:*",
"rn:promo:LIVE:subcategory:041-040-017:*",
"rn:promo:LIVE:subcategory:041-004-058:*",
"rn:promo:LIVE:subcategory:041-052-053:*",
"rn:promo:LIVE:subcategory:041-056-046:*",
"rn:promo:LIVE:subcategory:041-070-073:*",
"rn:promo:LIVE:subcategory:041-098-082:*",
"rn:promo:LIVE:subcategory:041-070-035:*",
"rn:promo:LIVE:subcategory:041-032-032:*",
"rn:promo:LIVE:subcategory:041-007-012:*",
"rn:promo:LIVE:subcategory:041-085-078:*",
"rn:promo:LIVE:subcategory:041-020-054:*",
"rn:promo:LIVE:subcategory:041-041-043:*",
"rn:promo:LIVE:subcategory:041-090-094:*",
"rn:promo:LIVE:subcategory:041-080-077:*",
"rn:promo:LIVE:subcategory:041-005-079:*",
"rn:promo:LIVE:subcategory:041-065-037:*",
"rn:promo:LIVE:subcategory:041-099-099:*",
"rn:promo:LIVE:subcategory:041-004-004:*",
"rn:promo:LIVE:subcategory:041-040-040:*",
"rn:promo:LIVE:subcategory:041-041-005:*",
"rn:promo:LIVE:subcategory:041-080-038:*",
"rn:promo:LIVE:subcategory:041-001-048:*",
"rn:promo:LIVE:subcategory:041-095-095:*",
"rn:promo:LIVE:subcategory:041-003-060:*",
"rn:promo:LIVE:subcategory:041-005-061:*",
"rn:promo:LIVE:subcategory:041-006-006:*",
"rn:promo:LIVE:subcategory:041-085-085:*",
"rn:promo:LIVE:subcategory:041-085-029:*",
"rn:promo:LIVE:subcategory:041-020-022:*",
"rn:promo:LIVE:subcategory:041-004-014:*",
"rn:promo:LIVE:subcategory:041-080-084:*",
"rn:promo:LIVE:subcategory:041-005-047:*",
"rn:promo:LIVE:subcategory:041-041-045:*",
"rn:promo:LIVE:subcategory:041-070-074:*",
"rn:promo:LIVE:subcategory:041-071-072:*",
"rn:promo:LIVE:subcategory:041-085-089:*",
"rn:promo:LIVE:subcategory:041-004-009:*",
"rn:promo:LIVE:subcategory:041-090-033:*",
"rn:promo:LIVE:subcategory:041-020-076:*",
"rn:promo:LIVE:subcategory:041-020-027:*",
"rn:promo:LIVE:subcategory:041-030-075:*",
"rn:promo:LIVE:subcategory:041-004-011:*",
"rn:promo:LIVE:subcategory:041-040-044:*",
"rn:promo:LIVE:subcategory:041-040-042:*",
"rn:promo:LIVE:subcategory:041-041-041:*",
"rn:promo:LIVE:subcategory:041-020-025:*",
"rn:promo:LIVE:subcategory:041-030-034:*",
"rn:promo:LIVE:subcategory:041-056-056:*",
"rn:promo:LIVE:subcategory:041-052-052:*",
"rn:promo:LIVE:subcategory:041-052-019:*",
"rn:promo:LIVE:subcategory:041-070-070:*",
"rn:promo:LIVE:subcategory:041-007-007:*",
"rn:promo:LIVE:subcategory:041-002-003:*",
"rn:promo:LIVE:subcategory:041-008-008:*",
"rn:promo:LIVE:subcategory:041-080-080:*",
"rn:promo:LIVE:subcategory:041-020-021:*",
"rn:promo:LIVE:subcategory:041-002-002:*",
"rn:promo:LIVE:subcategory:041-020-020:*",
"rn:promo:LIVE:subcategory:041-052-036:*",
"rn:promo:LIVE:subcategory:041-065-068:*",
"rn:promo:LIVE:subcategory:041-055-055:*",
"rn:promo:LIVE:subcategory:041-090-090:*",
"rn:promo:LIVE:subcategory:041-031-031:*",
"rn:promo:LIVE:subcategory:041-065-065:*",
"rn:promo:LIVE:subcategory:041-999-999:*",
"rn:promo:LIVE:subcategory:041-030-030:*",
"rn:promo:LIVE:subcategory:041-004-018:*",
"rn:promo:LIVE:subcategory:041-004-013:*",
"rn:promo:LIVE:subcategory:041-065-069:*",
"rn:promo:LIVE:subcategory:041-020-024:*",
"rn:promo:LIVE:subcategory:041-041-023:*",
"rn:promo:LIVE:subcategory:041-098-098:*",
"rn:promo:LIVE:subcategory:041-002-026:*",
"rn:promo:LIVE:subcategory:041-080-081:*",
"rn:promo:LIVE:subcategory:041-015-015:*",
"rn:promo:LIVE:subcategory:041-040-028:*"],
"description": "Policy for 041 in LIVE dataset. These are just sample resources and actions. This is not a complete list"}